omataxonomy/__init__.py
omataxonomy/build_db.py
omataxonomy/gtdb.py
omataxonomy/mnemonic.py
omataxonomy/query.py
omataxonomy-0.4.0.dist-info/LICENSE.txt
omataxonomy-0.4.0.dist-info/METADATA
omataxonomy-0.4.0.dist-info/WHEEL
omataxonomy-0.4.0.dist-info/RECORD
