Metadata-Version: 2.3
Name: omataxonomy
Version: 0.4.0
Summary: Package to work with combined NCBI and GTDB taxonomy
License: GPL-3.0
Author: Adrian Altenhoff
Author-email: adrian.altenhoff@inf.ethz.ch
Requires-Python: >=3.9,<3.13
Classifier: License :: OSI Approved :: GNU General Public License v3 (GPLv3)
Classifier: Programming Language :: Python :: 3
Classifier: Programming Language :: Python :: 3.9
Classifier: Programming Language :: Python :: 3.10
Classifier: Programming Language :: Python :: 3.11
Classifier: Programming Language :: Python :: 3.12
Requires-Dist: ete4 (>=4.3.0,<5.0.0)
Requires-Dist: numpy (>=2.0.0,<3.0.0)
Requires-Dist: requests (>=2.32.3,<3.0.0)
Requires-Dist: six (>=1.16.0,<2.0.0)
Requires-Dist: tqdm (>=4.64.1,<5.0.0)
